MANIFEST.in
setup.cfg
setup.py
references_finder/__init__.py
references_finder/all_alt_greek_15082023.csv
references_finder/mail_sender.py
references_finder/mto_148000_with_adress_newtriodi_23082023.csv
references_finder/obraz.py
references_finder/utils.py
references_finder.egg-info/PKG-INFO
references_finder.egg-info/SOURCES.txt
references_finder.egg-info/dependency_links.txt
references_finder.egg-info/not-zip-safe
references_finder.egg-info/top_level.txt