Metadata-Version: 1.0
Name: references-finder
Version: 0.3.1
Summary: Looking for similar words in Bible. Third Edition. This edition adds ancient Greek texts to the search programme.
Home-page: UNKNOWN
Author: UNKNOWN
Author-email: vl.sergiiy@gmail.com
License: UNKNOWN
Platform: UNKNOWN
